LICENSE
README.md
setup.py
nestify/__init__.py
nestify/nestify.py
nestify/recursive_processor.py
nestify.egg-info/PKG-INFO
nestify.egg-info/SOURCES.txt
nestify.egg-info/dependency_links.txt
nestify.egg-info/top_level.txt