Metadata-Version: 2.1
Name: nestify
Version: 0.0.1
Summary: transform flat key-path dictionaries into nested structures with ease
Home-page: https://github.com/Jyonn/nestify
Author: Jyonn Liu
Author-email: i@6-79.cn
License: MIT Licence
Keywords: dict,object
Platform: any
License-File: LICENSE
